{
    "China": [
        {
            "date": "2020-01-22, 12:00:00",
            "cases_sim": 594.5051636732096,
            "deaths_sim": 1.043979071368141
        },
        {
            "date": "2020-01-23, 00:00:00",
            "cases_sim": 702.405199961756,
            "deaths_sim": 2.277435689052473
        },
        {
            "date": "2020-01-23, 12:00:00",
            "cases_sim": 829.5383683465893,
            "deaths_sim": 3.734144138984042
        },
        {
            "date": "2020-01-24, 00:00:00",
            "cases_sim": 979.1954266343537,
            "deaths_sim": 5.453657432812358
        },
        {
            "date": "2020-01-24, 12:00:00",
            "cases_sim": 1155.176555177551,
            "deaths_sim": 7.482201877892092
        },
        {
            "date": "2020-01-25, 00:00:00",
            "cases_sim": 1361.8493116676912,
            "deaths_sim": 9.873673418616486
        },
        {
            "date": "2020-01-25, 12:00:00",
            "cases_sim": 1604.2047181001872,
            "deaths_sim": 12.69073246910307
        },
        {
            "date": "2020-01-26, 00:00:00",
            "cases_sim": 1887.9072200984208,
            "deaths_sim": 16.00598647680577
        },
        {
            "date": "2020-01-26, 12:00:00",
            "cases_sim": 2219.3325373136377,
            "deaths_sim": 19.903238953212142
        },
        {
            "date": "2020-01-27, 00:00:00",
            "cases_sim": 2605.585337900954,
            "deaths_sim": 24.478769541753035
        },
        {
            "date": "2020-01-27, 12:00:00",
            "cases_sim": 3054.486278326008,
            "deaths_sim": 29.842591327002253
        },
        {
            "date": "2020-01-28, 00:00:00",
            "cases_sim": 3574.5154129820908,
            "deaths_sim": 36.11960876849822
        },
        {
            "date": "2020-01-28, 12:00:00",
            "cases_sim": 4174.696609713758,
            "deaths_sim": 43.45057266278053
        },
        {
            "date": "2020-01-29, 00:00:00",
            "cases_sim": 4864.4059248908425,
            "deaths_sim": 51.99269860303007
        },
        {
            "date": "2020-01-29, 12:00:00",
            "cases_sim": 5653.086653478588,
            "deaths_sim": 61.91978505320981
        },
        {
            "date": "2020-01-30, 00:00:00",
            "cases_sim": 6549.855967643977,
            "deaths_sim": 73.42164066106913
        },
        {
            "date": "2020-01-30, 12:00:00",
            "cases_sim": 7562.993825158063,
            "deaths_sim": 86.70261407022794
        },
        {
            "date": "2020-01-31, 00:00:00",
            "cases_sim": 8699.315217592792,
            "deaths_sim": 101.97902137052422
        },
        {
            "date": "2020-01-31, 12:00:00",
            "cases_sim": 9963.442423972516,
            "deaths_sim": 119.4752955914936
        },
        {
            "date": "2020-02-01, 00:00:00",
            "cases_sim": 11357.014336459602,
            "deaths_sim": 139.4187477345083
        },
        {
            "date": "2020-02-01, 12:00:00",
            "cases_sim": 12877.893195154162,
            "deaths_sim": 162.03293479385778
        },
        {
            "date": "2020-02-02, 00:00:00",
            "cases_sim": 14519.451398437735,
            "deaths_sim": 187.52977538319874
        },
        {
            "date": "2020-02-02, 12:00:00",
            "cases_sim": 16270.03693381138,
            "deaths_sim": 216.10072663337573
        },
        {
            "date": "2020-02-03, 00:00:00",
            "cases_sim": 18112.719157055795,
            "deaths_sim": 247.9075146664721
        },
        {
            "date": "2020-02-03, 12:00:00",
            "cases_sim": 20025.401935017853,
            "deaths_sim": 283.07306375392375
        },
        {
            "date": "2020-02-04, 00:00:00",
            "cases_sim": 21981.356603110395,
            "deaths_sim": 321.673361373107
        },
        {
            "date": "2020-02-04, 12:00:00",
            "cases_sim": 23950.175840671596,
            "deaths_sim": 363.7309983139899
        },
        {
            "date": "2020-02-05, 00:00:00",
            "cases_sim": 25899.089904773282,
            "deaths_sim": 409.21102015435133
        },
        {
            "date": "2020-02-05, 12:00:00",
            "cases_sim": 27794.53092279343,
            "deaths_sim": 458.0195257064429
        },
        {
            "date": "2020-02-06, 00:00:00",
            "cases_sim": 29603.79174627624,
            "deaths_sim": 510.0051784891691
        },
        {
            "date": "2020-02-06, 12:00:00",
            "cases_sim": 31296.612272967082,
            "deaths_sim": 564.9635038564838
        },
        {
            "date": "2020-02-07, 00:00:00",
            "cases_sim": 32846.54076233128,
            "deaths_sim": 622.6435766599619
        },
        {
            "date": "2020-02-07, 12:00:00",
            "cases_sim": 34231.956041972764,
            "deaths_sim": 682.756503953993
        },
        {
            "date": "2020-02-08, 00:00:00",
            "cases_sim": 35436.688895932944,
            "deaths_sim": 744.9849988880984
        },
        {
            "date": "2020-02-08, 12:00:00",
            "cases_sim": 36450.23565199423,
            "deaths_sim": 808.9933296686131
        },
        {
            "date": "2020-02-09, 00:00:00",
            "cases_sim": 37267.60380243194,
            "deaths_sim": 874.4369974231375
        },
        {
            "date": "2020-02-09, 12:00:00",
            "cases_sim": 37888.861899192656,
            "deaths_sim": 940.9716236597193
        },
        {
            "date": "2020-02-10, 00:00:00",
            "cases_sim": 38318.48187778921,
            "deaths_sim": 1008.2606828158156
        },
        {
            "date": "2020-02-10, 12:00:00",
            "cases_sim": 38564.56301424307,
            "deaths_sim": 1075.9818720390908
        },
        {
            "date": "2020-02-11, 00:00:00",
            "cases_sim": 38638.016793039445,
            "deaths_sim": 1143.8320495579471
        },
        {
            "date": "2020-02-11, 12:00:00",
            "cases_sim": 38551.77567135989,
            "deaths_sim": 1211.5307836047762
        },
        {
            "date": "2020-02-12, 00:00:00",
            "cases_sim": 38320.070235435756,
            "deaths_sim": 1278.8226319917187
        },
        {
            "date": "2020-02-12, 12:00:00",
            "cases_sim": 37957.801655508585,
            "deaths_sim": 1345.4783196877745
        },
        {
            "date": "2020-02-13, 00:00:00",
            "cases_sim": 37480.021522303985,
            "deaths_sim": 1411.2950029642566
        },
        {
            "date": "2020-02-13, 12:00:00",
            "cases_sim": 36901.519879415275,
            "deaths_sim": 1476.0958101057086
        },
        {
            "date": "2020-02-14, 00:00:00",
            "cases_sim": 36236.51456298685,
            "deaths_sim": 1539.728836586669
        },
        {
            "date": "2020-02-14, 12:00:00",
            "cases_sim": 35498.43036775345,
            "deaths_sim": 1602.0657524536016
        },
        {
            "date": "2020-02-15, 00:00:00",
            "cases_sim": 34699.754415431824,
            "deaths_sim": 1663.0001557269059
        },
        {
            "date": "2020-02-15, 12:00:00",
            "cases_sim": 33851.95371882628,
            "deaths_sim": 1722.4457810416152
        },
        {
            "date": "2020-02-16, 00:00:00",
            "cases_sim": 32965.441700223084,
            "deaths_sim": 1780.3346494928185
        },
        {
            "date": "2020-02-16, 12:00:00",
            "cases_sim": 32049.581845091518,
            "deaths_sim": 1836.6152248971523
        },
        {
            "date": "2020-02-17, 00:00:00",
            "cases_sim": 31112.718390687813,
            "deaths_sim": 1891.2506239449276
        },
        {
            "date": "2020-02-17, 12:00:00",
            "cases_sim": 30162.22571871603,
            "deaths_sim": 1944.2169130880952
        },
        {
            "date": "2020-02-18, 00:00:00",
            "cases_sim": 29204.569789997284,
            "deaths_sim": 1995.5015133103848
        },
        {
            "date": "2020-02-18, 12:00:00",
            "cases_sim": 28245.376444838486,
            "deaths_sim": 2045.1017248361081
        },
        {
            "date": "2020-02-19, 00:00:00",
            "cases_sim": 27289.50266129964,
            "deaths_sim": 2093.023376971837
        },
        {
            "date": "2020-02-19, 12:00:00",
            "cases_sim": 26341.10791159326,
            "deaths_sim": 2139.279603253278
        },
        {
            "date": "2020-02-20, 00:00:00",
            "cases_sim": 25403.72359931412,
            "deaths_sim": 2183.889738527196
        },
        {
            "date": "2020-02-20, 12:00:00",
            "cases_sim": 24480.31922118996,
            "deaths_sim": 2226.878332216488
        },
        {
            "date": "2020-02-21, 00:00:00",
            "cases_sim": 23573.36440397973,
            "deaths_sim": 2268.274270524969
        },
        {
            "date": "2020-02-21, 12:00:00",
            "cases_sim": 22684.886347171545,
            "deaths_sim": 2308.1099995142463
        },
        {
            "date": "2020-02-22, 00:00:00",
            "cases_sim": 21816.522480136824,
            "deaths_sim": 2346.4208406490343
        },
        {
            "date": "2020-02-22, 12:00:00",
            "cases_sim": 20969.56834009175,
            "deaths_sim": 2383.2443904184242
        },
        {
            "date": "2020-02-23, 00:00:00",
            "cases_sim": 20145.020812881005,
            "deaths_sim": 2418.619995890009
        },
        {
            "date": "2020-02-23, 12:00:00",
            "cases_sim": 19343.616967209637,
            "deaths_sim": 2452.5882984587465
        },
        {
            "date": "2020-02-24, 00:00:00",
            "cases_sim": 18565.868766515974,
            "deaths_sim": 2485.190838551509
        },
        {
            "date": "2020-02-24, 12:00:00",
            "cases_sim": 17812.09397065539,
            "deaths_sim": 2516.469714596442
        },
        {
            "date": "2020-02-25, 00:00:00",
            "cases_sim": 17082.443549272455,
            "deaths_sim": 2546.4672901314984
        },
        {
            "date": "2020-02-25, 12:00:00",
            "cases_sim": 16376.925925771573,
            "deaths_sim": 2575.225943486526
        },
        {
            "date": "2020-02-26, 00:00:00",
            "cases_sim": 15695.428359342488,
            "deaths_sim": 2602.7878550131995
        },
        {
            "date": "2020-02-26, 12:00:00",
            "cases_sim": 15037.735755687476,
            "deaths_sim": 2629.1948273474745
        },
        {
            "date": "2020-02-27, 00:00:00",
            "cases_sim": 14403.547177186707,
            "deaths_sim": 2654.4881346646707
        },
        {
            "date": "2020-02-27, 12:00:00",
            "cases_sim": 13792.490301858292,
            "deaths_sim": 2678.7083973251697
        },
        {
            "date": "2020-02-28, 00:00:00",
            "cases_sim": 13204.134058752521,
            "deaths_sim": 2701.89547870846
        },
        {
            "date": "2020-02-28, 12:00:00",
            "cases_sim": 12637.999646136921,
            "deaths_sim": 2724.0884013956334
        },
        {
            "date": "2020-02-29, 00:00:00",
            "cases_sim": 12093.570118480711,
            "deaths_sim": 2745.32528018708
        },
        {
            "date": "2020-02-29, 12:00:00",
            "cases_sim": 11570.298709139122,
            "deaths_sim": 2765.6432697352056
        },
        {
            "date": "2020-03-01, 00:00:00",
            "cases_sim": 11067.61603793476,
            "deaths_sim": 2785.078524834005
        },
        {
            "date": "2020-03-01, 12:00:00",
            "cases_sim": 10584.93633660016,
            "deaths_sim": 2803.666171640802
        },
        {
            "date": "2020-03-02, 00:00:00",
            "cases_sim": 10121.662810281563,
            "deaths_sim": 2821.440288313046
        },
        {
            "date": "2020-03-02, 12:00:00",
            "cases_sim": 9677.19223996165,
            "deaths_sim": 2838.4338937271773
        },
        {
            "date": "2020-03-03, 00:00:00",
            "cases_sim": 9250.918918663841,
            "deaths_sim": 2854.678943109654
        },
        {
            "date": "2020-03-03, 12:00:00",
            "cases_sim": 8842.238003561526,
            "deaths_sim": 2870.2063295544394
        },
        {
            "date": "2020-03-04, 00:00:00",
            "cases_sim": 8450.548356532943,
            "deaths_sim": 2885.0458905286387
        },
        {
            "date": "2020-03-04, 12:00:00",
            "cases_sim": 8075.254937175287,
            "deaths_sim": 2899.2264185803806
        },
        {
            "date": "2020-03-05, 00:00:00",
            "cases_sim": 7715.770804720442,
            "deaths_sim": 2912.775675562157
        },
        {
            "date": "2020-03-05, 12:00:00",
            "cases_sim": 7371.518778584468,
            "deaths_sim": 2925.7204097701674
        },
        {
            "date": "2020-03-06, 00:00:00",
            "cases_sim": 7041.932801344252,
            "deaths_sim": 2938.0863754771117
        },
        {
            "date": "2020-03-06, 12:00:00",
            "cases_sim": 6726.459042685058,
            "deaths_sim": 2949.898354403569
        },
        {
            "date": "2020-03-07, 00:00:00",
            "cases_sim": 6424.5567782263615,
            "deaths_sim": 2961.1801787326367
        },
        {
            "date": "2020-03-07, 12:00:00",
            "cases_sim": 6135.699073041644,
            "deaths_sim": 2971.9547553248585
        },
        {
            "date": "2020-03-08, 00:00:00",
            "cases_sim": 5859.373296078938,
            "deaths_sim": 2982.2440908365047
        },
        {
            "date": "2020-03-08, 12:00:00",
            "cases_sim": 5595.081488507103,
            "deaths_sim": 2992.0693174846815
        },
        {
            "date": "2020-03-09, 00:00:00",
            "cases_sim": 5342.340606208574,
            "deaths_sim": 3001.450719238271
        },
        {
            "date": "2020-03-09, 12:00:00",
            "cases_sim": 5100.682654168398,
            "deaths_sim": 3010.407758244865
        },
        {
            "date": "2020-03-10, 00:00:00",
            "cases_sim": 4869.654728332474,
            "deaths_sim": 3018.959101331201
        },
        {
            "date": "2020-03-10, 12:00:00",
            "cases_sim": 4648.818978590347,
            "deaths_sim": 3027.122646438599
        },
        {
            "date": "2020-03-11, 00:00:00",
            "cases_sim": 4437.752504848807,
            "deaths_sim": 3034.9155488758947
        },
        {
            "date": "2020-03-11, 12:00:00",
            "cases_sim": 4236.04719667489,
            "deaths_sim": 3042.354247290779
        },
        {
            "date": "2020-03-12, 00:00:00",
            "cases_sim": 4043.309525676533,
            "deaths_sim": 3049.4544892765493
        },
        {
            "date": "2020-03-12, 12:00:00",
            "cases_sim": 3859.1602986351363,
            "deaths_sim": 3056.23135654535
        },
        {
            "date": "2020-03-13, 00:00:00",
            "cases_sim": 3683.23437838793,
            "deaths_sim": 3062.6992896112674
        },
        {
            "date": "2020-03-13, 12:00:00",
            "cases_sim": 3515.180378562974,
            "deaths_sim": 3068.872111937367
        },
        {
            "date": "2020-03-14, 00:00:00",
            "cases_sim": 3354.6603374814135,
            "deaths_sim": 3074.7630535100875
        },
        {
            "date": "2020-03-14, 12:00:00",
            "cases_sim": 3201.3493758475847,
            "deaths_sim": 3080.3847738125196
        },
        {
            "date": "2020-03-15, 00:00:00",
            "cases_sim": 3054.935342236547,
            "deaths_sim": 3085.749384175149
        },
        {
            "date": "2020-03-15, 12:00:00",
            "cases_sim": 2915.118449850749,
            "deaths_sim": 3090.868469488723
        },
        {
            "date": "2020-03-16, 00:00:00",
            "cases_sim": 2781.6109075442214,
            "deaths_sim": 3095.75310926918
        },
        {
            "date": "2020-03-16, 12:00:00",
            "cases_sim": 2654.1365476962487,
            "deaths_sim": 3100.4138980691096
        },
        {
            "date": "2020-03-17, 00:00:00",
            "cases_sim": 2532.43045315026,
            "deaths_sim": 3104.860965234093
        },
        {
            "date": "2020-03-17, 12:00:00",
            "cases_sim": 2416.238585111732,
            "deaths_sim": 3109.1039940056235
        },
        {
            "date": "2020-03-18, 00:00:00",
            "cases_sim": 2305.3174136160674,
            "deaths_sim": 3113.1522399751043
        },
        {
            "date": "2020-03-18, 12:00:00",
            "cases_sim": 2199.4335519290594,
            "deaths_sim": 3117.0145488958406
        },
        {
            "date": "2020-03-19, 00:00:00",
            "cases_sim": 2098.363396024681,
            "deaths_sim": 3120.6993738619344
        },
        {
            "date": "2020-03-19, 12:00:00",
            "cases_sim": 2001.8927700939537,
            "deaths_sim": 3124.214791864679
        },
        {
            "date": "2020-03-20, 00:00:00",
            "cases_sim": 1909.816578871402,
            "deaths_sim": 3127.5685197384196
        },
        {
            "date": "2020-03-20, 12:00:00",
            "cases_sim": 1821.9384674193532,
            "deaths_sim": 3130.767929508983
        },
        {
            "date": "2020-03-21, 00:00:00",
            "cases_sim": 1738.070488882574,
            "deaths_sim": 3133.8200631586637
        },
        {
            "date": "2020-03-21, 12:00:00",
            "cases_sim": 1658.0327806143625,
            "deaths_sim": 3136.731646822477
        },
        {
            "date": "2020-03-22, 00:00:00",
            "cases_sim": 1581.653248978249,
            "deaths_sim": 3139.5091044309065
        }
    ]
}